{
  "dictionary": [
    {
      "display": "テスト",
      "yomi": "てすと",
      "sentenceJp": "テスト",
      "sentenceRm": [
        "tesuto"
      ]
    },
    {
      "display": "日本語",
      "yomi": "にほんご",
      "sentenceJp": "日本語",
      "sentenceRm": [
        "nihongo",
        "nihonngo"
      ]
    },
    {
      "display": "自作キーボード",
      "yomi": "じさくきーぼーど",
      "sentenceJp": "自作キーボード",
      "sentenceRm": [
        "zisakuki-bo-do",
        "jisakuki-bo-do"
      ]
    },
    {
      "display": "天正遣欧使節",
      "yomi": "てんしょうけんおうしせつ",
      "sentenceJp": "天正遣欧使節",
      "sentenceRm": [
        "tensyoukennousisetu",
        "tenshoukennousisetu",
        "tensixyoukennousisetu",
        "tenshixyoukennousisetu",
        "tennsyoukennousisetu",
        "tennshoukennousisetu",
        "tennsixyoukennousisetu",
        "tennshixyoukennousisetu",
        "tensyoukennoushisetu",
        "tenshoukennoushisetu",
        "tensixyoukennoushisetu",
        "tenshixyoukennoushisetu",
        "tennsyoukennoushisetu",
        "tennshoukennoushisetu",
        "tennsixyoukennoushisetu",
        "tennshixyoukennoushisetu",
        "tensyoukennousisetsu",
        "tenshoukennousisetsu",
        "tensixyoukennousisetsu",
        "tenshixyoukennousisetsu",
        "tennsyoukennousisetsu",
        "tennshoukennousisetsu",
        "tennsixyoukennousisetsu",
        "tennshixyoukennousisetsu",
        "tensyoukennoushisetsu",
        "tenshoukennoushisetsu",
        "tensixyoukennoushisetsu",
        "tenshixyoukennoushisetsu",
        "tennsyoukennoushisetsu",
        "tennshoukennoushisetsu",
        "tennsixyoukennoushisetsu",
        "tennshixyoukennoushisetsu"
      ]
    },
    {
      "display": "嘘みたいにでかい亀が発見される",
      "yomi": "うそみたいにでかいかめがはっけんされる",
      "sentenceJp": "嘘みたいにでかい亀が発見される",
      "sentenceRm": [
        "usomitainidekaikamegahakkensareru",
        "usomitainidekaikamegahaxtukensareru",
        "usomitainidekaikamegahaxtsukensareru",
        "usomitainidekaikamegahakkennsareru",
        "usomitainidekaikamegahaxtukennsareru",
        "usomitainidekaikamegahaxtsukennsareru"
      ]
    },
    {
      "display": "大型の台風",
      "yomi": "おおがたのたいふう",
      "sentenceJp": "大型の台風",
      "sentenceRm": [
        "oogatanotaihuu",
        "oogatanotaifuu"
      ]
    },
    {
      "display": "ストリートビュー",
      "yomi": "すとりーとびゅー",
      "sentenceJp": "ストリートビュー",
      "sentenceRm": [
        "sutori-tobyu-",
        "sutori-tobixyu-"
      ]
    },
    {
      "display": "面白い製品",
      "yomi": "おもしろいせいひん",
      "sentenceJp": "面白い製品",
      "sentenceRm": [
        "omosiroiseihinn",
        "omoshiroiseihinn"
      ]
    },
    {
      "display": "必殺技コマンド",
      "yomi": "ひっさつわざこまんど",
      "sentenceJp": "必殺技コマンド",
      "sentenceRm": [
        "hissatuwazakomando",
        "hixtusatuwazakomando",
        "hixtsusatuwazakomando",
        "hissatsuwazakomando",
        "hixtusatsuwazakomando",
        "hixtsusatsuwazakomando",
        "hissatuwazakomanndo",
        "hixtusatuwazakomanndo",
        "hixtsusatuwazakomanndo",
        "hissatsuwazakomanndo",
        "hixtusatsuwazakomanndo",
        "hixtsusatsuwazakomanndo"
      ]
    },
    {
      "display": "ナレーション",
      "yomi": "なれーしょん",
      "sentenceJp": "ナレーション",
      "sentenceRm": [
        "nare-syonn",
        "nare-shonn",
        "nare-sixyonn",
        "nare-shixyonn"
      ]
    },
    {
      "display": "存在感つよつよ",
      "yomi": "そんざいかんつよつよ",
      "sentenceJp": "存在感つよつよ",
      "sentenceRm": [
        "sonzaikantuyotuyo",
        "sonnzaikantuyotuyo",
        "sonzaikantsuyotuyo",
        "sonnzaikantsuyotuyo",
        "sonzaikanntuyotuyo",
        "sonnzaikanntuyotuyo",
        "sonzaikanntsuyotuyo",
        "sonnzaikanntsuyotuyo",
        "sonzaikantuyotsuyo",
        "sonnzaikantuyotsuyo",
        "sonzaikantsuyotsuyo",
        "sonnzaikantsuyotsuyo",
        "sonzaikanntuyotsuyo",
        "sonnzaikanntuyotsuyo",
        "sonzaikanntsuyotsuyo",
        "sonnzaikanntsuyotsuyo"
      ]
    },
    {
      "display": "ハードルが上がる",
      "yomi": "はーどるがあがる",
      "sentenceJp": "ハードルが上がる",
      "sentenceRm": [
        "ha-dorugaagaru"
      ]
    },
    {
      "display": "大好評開催中",
      "yomi": "だいこうひょうかいさいちゅう",
      "sentenceJp": "大好評開催中",
      "sentenceRm": [
        "daikouhyoukaisaityuu",
        "daikouhixyoukaisaityuu",
        "daikouhyoukaisaichuu",
        "daikouhixyoukaisaichuu",
        "daikouhyoukaisaitixyuu",
        "daikouhixyoukaisaitixyuu",
        "daikouhyoukaisaichixyuu",
        "daikouhixyoukaisaichixyuu"
      ]
    },
    {
      "display": "本日の資料です",
      "yomi": "ほんじつのしりょうです",
      "sentenceJp": "本日の資料です",
      "sentenceRm": [
        "honzitunosiryoudesu",
        "honjitunosiryoudesu",
        "honnzitunosiryoudesu",
        "honnjitunosiryoudesu",
        "honzitsunosiryoudesu",
        "honjitsunosiryoudesu",
        "honnzitsunosiryoudesu",
        "honnjitsunosiryoudesu",
        "honzitunoshiryoudesu",
        "honjitunoshiryoudesu",
        "honnzitunoshiryoudesu",
        "honnjitunoshiryoudesu",
        "honzitsunoshiryoudesu",
        "honjitsunoshiryoudesu",
        "honnzitsunoshiryoudesu",
        "honnjitsunoshiryoudesu",
        "honzitunosirixyoudesu",
        "honjitunosirixyoudesu",
        "honnzitunosirixyoudesu",
        "honnjitunosirixyoudesu",
        "honzitsunosirixyoudesu",
        "honjitsunosirixyoudesu",
        "honnzitsunosirixyoudesu",
        "honnjitsunosirixyoudesu",
        "honzitunoshirixyoudesu",
        "honjitunoshirixyoudesu",
        "honnzitunoshirixyoudesu",
        "honnjitunoshirixyoudesu",
        "honzitsunoshirixyoudesu",
        "honjitsunoshirixyoudesu",
        "honnzitsunoshirixyoudesu",
        "honnjitsunoshirixyoudesu"
      ]
    },
    {
      "display": "ダニングクルーガー効果",
      "yomi": "だにんぐくるーがーこうか",
      "sentenceJp": "ダニングクルーガー効果",
      "sentenceRm": [
        "daningukuru-ga-kouka",
        "daninngukuru-ga-kouka"
      ]
    },
    {
      "display": "最強ゴスペル女子高生",
      "yomi": "さいきょうごすぺるじょしこうせい",
      "sentenceJp": "最強ゴスペル女子高生",
      "sentenceRm": [
        "saikyougosuperujosikousei",
        "saikixyougosuperujosikousei",
        "saikyougosuperuzyosikousei",
        "saikixyougosuperuzyosikousei",
        "saikyougosuperujixyosikousei",
        "saikixyougosuperujixyosikousei",
        "saikyougosuperuzixyosikousei",
        "saikixyougosuperuzixyosikousei",
        "saikyougosuperujoshikousei",
        "saikixyougosuperujoshikousei",
        "saikyougosuperuzyoshikousei",
        "saikixyougosuperuzyoshikousei",
        "saikyougosuperujixyoshikousei",
        "saikixyougosuperujixyoshikousei",
        "saikyougosuperuzixyoshikousei",
        "saikixyougosuperuzixyoshikousei"
      ]
    },
    {
      "display": "セキュリティ界隈",
      "yomi": "せきゅりてぃかいわい",
      "sentenceJp": "セキュリティ界隈",
      "sentenceRm": [
        "sekyurithikaiwai",
        "sekixyurithikaiwai",
        "sekyuritexikaiwai",
        "sekixyuritexikaiwai"
      ]
    },
    {
      "display": "優秀なエンジニア",
      "yomi": "ゆうしゅうなえんじにあ",
      "sentenceJp": "優秀なエンジニア",
      "sentenceRm": [
        "yuusyuunaenzinia",
        "yuushuunaenzinia",
        "yuusixyuunaenzinia",
        "yuushixyuunaenzinia",
        "yuusyuunaenjinia",
        "yuushuunaenjinia",
        "yuusixyuunaenjinia",
        "yuushixyuunaenjinia",
        "yuusyuunaennzinia",
        "yuushuunaennzinia",
        "yuusixyuunaennzinia",
        "yuushixyuunaennzinia",
        "yuusyuunaennjinia",
        "yuushuunaennjinia",
        "yuusixyuunaennjinia",
        "yuushixyuunaennjinia"
      ]
    },
    {
      "display": "比類なき高性能",
      "yomi": "ひるいなきこうせいのう",
      "sentenceJp": "比類なき高性能",
      "sentenceRm": [
        "hiruinakikouseinou"
      ]
    },
    {
      "display": "割増特急コース",
      "yomi": "わりましとっきゅうこーす",
      "sentenceJp": "割増特急コース",
      "sentenceRm": [
        "warimasitokkyuuko-su",
        "warimashitokkyuuko-su",
        "warimasitokkixyuuko-su",
        "warimashitokkixyuuko-su",
        "warimasitoxtukyuuko-su",
        "warimashitoxtukyuuko-su",
        "warimasitoxtukixyuuko-su",
        "warimashitoxtukixyuuko-su",
        "warimasitoxtsukyuuko-su",
        "warimashitoxtsukyuuko-su",
        "warimasitoxtsukixyuuko-su",
        "warimashitoxtsukixyuuko-su"
      ]
    },
    {
      "display": "撲殺天使ドクロちゃん",
      "yomi": "ぼくさつてんしどくろちゃん",
      "sentenceJp": "撲殺天使ドクロちゃん",
      "sentenceRm": [
        "bokusatutensidokurotyann",
        "bokusatsutensidokurotyann",
        "bokusatutenshidokurotyann",
        "bokusatsutenshidokurotyann",
        "bokusatutennsidokurotyann",
        "bokusatsutennsidokurotyann",
        "bokusatutennshidokurotyann",
        "bokusatsutennshidokurotyann",
        "bokusatutensidokurochann",
        "bokusatsutensidokurochann",
        "bokusatutenshidokurochann",
        "bokusatutennsidokurochann",
        "bokusatsutennsidokurochann",
        "bokusatutennshidokurochann",
        "bokusatsutennshidokurochann",
        "bokusatutensidokurotixyann",
        "bokusatsutensidokurotixyann",
        "bokusatutenshidokurotixyann",
        "bokusatsutenshidokurotixyann",
        "bokusatutennsidokurotixyann",
        "bokusatsutennsidokurotixyann",
        "bokusatutennshidokurotixyann",
        "bokusatsutennshidokurotixyann",
        "bokusatutensidokurochixyann",
        "bokusatsutensidokurochixyann",
        "bokusatutenshidokurochixyann",
        "bokusatsutenshidokurochixyann",
        "bokusatutennsidokurochixyann",
        "bokusatsutennsidokurochixyann",
        "bokusatutennshidokurochixyann",
        "bokusatsutennshidokurochixyann"
      ]
    },
    {
      "display": "長野と群馬の県境",
      "yomi": "ながのとぐんまのけんきょう",
      "sentenceJp": "長野と群馬の県境",
      "sentenceRm": [
        "naganotogunmanokenkyou",
        "naganotogunnmanokenkyou",
        "naganotogunmanokenkixyou",
        "naganotogunnmanokenkixyou",
        "naganotogunmanokennkyou",
        "naganotogunnmanokennkyou",
        "naganotogunmanokennkixyou",
        "naganotogunnmanokennkixyou"
      ]
    },
    {
      "display": "シェル芸",
      "yomi": "しぇるげい",
      "sentenceJp": "シェル芸",
      "sentenceRm": [
        "syerugei",
        "sherugei",
        "sixyerugei",
        "shixyerugei"
      ]
    },
    {
      "display": "ニューヨーク株式市場",
      "yomi": "にゅーよーくかぶしきしじょう",
      "sentenceJp": "ニューヨーク株式市場",
      "sentenceRm": [
        "nyu-yo-kukabusikisijou",
        "nixyu-yo-kukabusikisijou",
        "nyu-yo-kukabushikisijou",
        "nixyu-yo-kukabushikisijou",
        "nyu-yo-kukabusikishijou",
        "nixyu-yo-kukabusikishijou",
        "nyu-yo-kukabushikishijou",
        "nixyu-yo-kukabushikishijou",
        "nyu-yo-kukabusikisizyou",
        "nixyu-yo-kukabusikisizyou",
        "nyu-yo-kukabushikisizyou",
        "nixyu-yo-kukabushikisizyou",
        "nyu-yo-kukabusikishizyou",
        "nixyu-yo-kukabusikishizyou",
        "nyu-yo-kukabushikishizyou",
        "nixyu-yo-kukabushikishizyou",
        "nyu-yo-kukabusikisijixyou",
        "nixyu-yo-kukabusikisijixyou",
        "nyu-yo-kukabushikisijixyou",
        "nixyu-yo-kukabushikisijixyou",
        "nyu-yo-kukabusikishijixyou",
        "nixyu-yo-kukabusikishijixyou",
        "nyu-yo-kukabushikishijixyou",
        "nixyu-yo-kukabushikishijixyou",
        "nyu-yo-kukabusikisizixyou",
        "nixyu-yo-kukabusikisizixyou",
        "nyu-yo-kukabushikisizixyou",
        "nixyu-yo-kukabushikisizixyou",
        "nyu-yo-kukabusikishizixyou",
        "nixyu-yo-kukabusikishizixyou",
        "nyu-yo-kukabushikishizixyou",
        "nixyu-yo-kukabushikishizixyou"
      ]
    },
    {
      "display": "人事総務部長",
      "yomi": "じんじそうむぶちょう",
      "sentenceJp": "人事総務部長",
      "sentenceRm": [
        "zinzisoumubutyou",
        "jinzisoumubutyou",
        "zinjisoumubutyou",
        "jinjisoumubutyou",
        "zinnzisoumubutyou",
        "jinnzisoumubutyou",
        "zinnjisoumubutyou",
        "jinnjisoumubutyou",
        "zinzisoumubuchou",
        "jinzisoumubuchou",
        "zinjisoumubuchou",
        "jinjisoumubuchou",
        "zinnzisoumubuchou",
        "jinnzisoumubuchou",
        "zinnjisoumubuchou",
        "jinnjisoumubuchou",
        "zinzisoumubutixyou",
        "jinzisoumubutixyou",
        "zinjisoumubutixyou",
        "jinjisoumubutixyou",
        "zinnzisoumubutixyou",
        "jinnzisoumubutixyou",
        "zinnjisoumubutixyou",
        "jinnjisoumubutixyou",
        "zinzisoumubuchixyou",
        "jinzisoumubuchixyou",
        "zinjisoumubuchixyou",
        "jinjisoumubuchixyou",
        "zinnzisoumubuchixyou",
        "jinnzisoumubuchixyou",
        "zinnjisoumubuchixyou",
        "jinnjisoumubuchixyou"
      ]
    },
    {
      "display": "コミックマーケット",
      "yomi": "こみっくまーけっと",
      "sentenceJp": "コミックマーケット",
      "sentenceRm": [
        "komikkuma-ketto",
        "komixtukuma-ketto",
        "komixtsukuma-ketto",
        "komikkuma-kextuto",
        "komixtukuma-kextuto",
        "komixtsukuma-kextuto",
        "komikkuma-kextsuto",
        "komixtukuma-kextsuto",
        "komixtsukuma-kextsuto"
      ]
    },
    {
      "display": "早期解決",
      "yomi": "そうきかいけつ",
      "sentenceJp": "早期解決",
      "sentenceRm": [
        "soukikaiketu",
        "soukikaiketsu"
      ]
    },
    {
      "display": "菓子パン落下監視委員会",
      "yomi": "かしぱんらっかかんしいいんかい",
      "sentenceJp": "菓子パン落下監視委員会",
      "sentenceRm": [
        "kasipanrakkakansiiinkai",
        "kashipanrakkakansiiinkai",
        "kasipannrakkakansiiinkai",
        "kashipannrakkakansiiinkai",
        "kasipanraxtukakansiiinkai",
        "kashipanraxtukakansiiinkai",
        "kasipannraxtukakansiiinkai",
        "kashipannraxtukakansiiinkai",
        "kasipanraxtsukakansiiinkai",
        "kashipanraxtsukakansiiinkai",
        "kasipannraxtsukakansiiinkai",
        "kashipannraxtsukakansiiinkai",
        "kasipanrakkakanshiiinkai",
        "kashipanrakkakanshiiinkai",
        "kasipannrakkakanshiiinkai",
        "kashipannrakkakanshiiinkai",
        "kasipanraxtukakanshiiinkai",
        "kashipanraxtukakanshiiinkai",
        "kasipannraxtukakanshiiinkai",
        "kashipannraxtukakanshiiinkai",
        "kasipanraxtsukakanshiiinkai",
        "kashipanraxtsukakanshiiinkai",
        "kasipannraxtsukakanshiiinkai",
        "kashipannraxtsukakanshiiinkai",
        "kasipanrakkakannsiiinkai",
        "kashipanrakkakannsiiinkai",
        "kasipannrakkakannsiiinkai",
        "kashipannrakkakannsiiinkai",
        "kasipanraxtukakannsiiinkai",
        "kashipanraxtukakannsiiinkai",
        "kasipannraxtukakannsiiinkai",
        "kashipannraxtukakannsiiinkai",
        "kasipanraxtsukakannsiiinkai",
        "kashipanraxtsukakannsiiinkai",
        "kasipannraxtsukakannsiiinkai",
        "kashipannraxtsukakannsiiinkai",
        "kasipanrakkakannshiiinkai",
        "kashipanrakkakannshiiinkai",
        "kasipannrakkakannshiiinkai",
        "kashipannrakkakannshiiinkai",
        "kasipanraxtukakannshiiinkai",
        "kashipanraxtukakannshiiinkai",
        "kasipannraxtukakannshiiinkai",
        "kashipannraxtukakannshiiinkai",
        "kasipanraxtsukakannshiiinkai",
        "kashipanraxtsukakannshiiinkai",
        "kasipannraxtsukakannshiiinkai",
        "kashipannraxtsukakannshiiinkai",
        "kasipanrakkakansiiinnkai",
        "kashipanrakkakansiiinnkai",
        "kasipannrakkakansiiinnkai",
        "kashipannrakkakansiiinnkai",
        "kasipanraxtukakansiiinnkai",
        "kashipanraxtukakansiiinnkai",
        "kasipannraxtukakansiiinnkai",
        "kashipannraxtukakansiiinnkai",
        "kasipanraxtsukakansiiinnkai",
        "kashipanraxtsukakansiiinnkai",
        "kasipannraxtsukakansiiinnkai",
        "kashipannraxtsukakansiiinnkai",
        "kasipanrakkakanshiiinnkai",
        "kashipanrakkakanshiiinnkai",
        "kasipannrakkakanshiiinnkai",
        "kashipannrakkakanshiiinnkai",
        "kasipanraxtukakanshiiinnkai",
        "kashipanraxtukakanshiiinnkai",
        "kasipannraxtukakanshiiinnkai",
        "kashipannraxtukakanshiiinnkai",
        "kasipanraxtsukakanshiiinnkai",
        "kashipanraxtsukakanshiiinnkai",
        "kasipannraxtsukakanshiiinnkai",
        "kashipannraxtsukakanshiiinnkai",
        "kasipanrakkakannsiiinnkai",
        "kashipanrakkakannsiiinnkai",
        "kasipannrakkakannsiiinnkai",
        "kashipannrakkakannsiiinnkai",
        "kasipanraxtukakannsiiinnkai",
        "kashipanraxtukakannsiiinnkai",
        "kasipannraxtukakannsiiinnkai",
        "kashipannraxtukakannsiiinnkai",
        "kasipanraxtsukakannsiiinnkai",
        "kashipanraxtsukakannsiiinnkai",
        "kasipannraxtsukakannsiiinnkai",
        "kashipannraxtsukakannsiiinnkai",
        "kasipanrakkakannshiiinnkai",
        "kashipanrakkakannshiiinnkai",
        "kasipannrakkakannshiiinnkai",
        "kashipannrakkakannshiiinnkai",
        "kasipanraxtukakannshiiinnkai",
        "kashipanraxtukakannshiiinnkai",
        "kasipannraxtukakannshiiinnkai",
        "kashipannraxtukakannshiiinnkai",
        "kasipanraxtsukakannshiiinnkai",
        "kashipanraxtsukakannshiiinnkai",
        "kasipannraxtsukakannshiiinnkai",
        "kashipannraxtsukakannshiiinnkai"
      ]
    },
    {
      "display": "お風呂で熱唱",
      "yomi": "おふろでねっしょう",
      "sentenceJp": "お風呂で熱唱",
      "sentenceRm": [
        "ohurodenessyou",
        "ofurodenessyou",
        "ohurodenesshou",
        "ofurodenesshou",
        "ohurodenessixyou",
        "ofurodenessixyou",
        "ohurodenesshixyou",
        "ofurodenesshixyou",
        "ohurodenextusyou",
        "ofurodenextusyou",
        "ohurodenextushou",
        "ofurodenextushou",
        "ohurodenextusixyou",
        "ofurodenextusixyou",
        "ohurodenextushixyou",
        "ofurodenextushixyou",
        "ohurodenextsusyou",
        "ofurodenextsusyou",
        "ohurodenextsushou",
        "ofurodenextsushou",
        "ohurodenextsusixyou",
        "ofurodenextsusixyou",
        "ohurodenextsushixyou",
        "ofurodenextsushixyou"
      ]
    },
    {
      "display": "無水エタノール",
      "yomi": "むすいえたのーる",
      "sentenceJp": "無水エタノール",
      "sentenceRm": [
        "musuietano-ru"
      ]
    },
    {
      "display": "神田明神",
      "yomi": "かんだみょうじん",
      "sentenceJp": "神田明神",
      "sentenceRm": [
        "kandamyouzinn",
        "kanndamyouzinn",
        "kandamixyouzinn",
        "kanndamixyouzinn",
        "kandamyoujinn",
        "kanndamyoujinn",
        "kandamixyoujinn",
        "kanndamixyoujinn"
      ]
    },
    {
      "display": "空前絶後",
      "yomi": "くうぜんぜつご",
      "sentenceJp": "空前絶後",
      "sentenceRm": [
        "kuuzenzetugo",
        "kuuzennzetugo",
        "kuuzenzetsugo",
        "kuuzennzetsugo"
      ]
    },
    {
      "display": "クッソ汚い字",
      "yomi": "くっそきたないじ",
      "sentenceJp": "クッソ汚い字",
      "sentenceRm": [
        "kussokitanaizi",
        "kuxtusokitanaizi",
        "kuxtsusokitanaizi",
        "kussokitanaiji",
        "kuxtusokitanaiji",
        "kuxtsusokitanaiji"
      ]
    },
    {
      "display": "最新のフレームワーク",
      "yomi": "さいしんのふれーむわーく",
      "sentenceJp": "最新のフレームワーク",
      "sentenceRm": [
        "saisinnnohure-muwa-ku",
        "saishinnnohure-muwa-ku",
        "saisinnnofure-muwa-ku",
        "saishinnnofure-muwa-ku"
      ]
    },
    {
      "display": "東京ディズニーリゾート",
      "yomi": "とうきょうでぃずにーりぞーと",
      "sentenceJp": "東京ディズニーリゾート",
      "sentenceRm": [
        "toukyoudhizuni-rizo-to",
        "toukixyoudhizuni-rizo-to",
        "toukyoudexizuni-rizo-to",
        "toukixyoudexizuni-rizo-to"
      ]
    },
    {
      "display": "完全に一致",
      "yomi": "かんぜんにいっち",
      "sentenceJp": "完全に一致",
      "sentenceRm": [
        "kanzennniitti",
        "kannzennniitti",
        "kanzennniicchi",
        "kannzennniicchi",
        "kanzennniixtuti",
        "kannzennniixtuti",
        "kanzennniixtuchi",
        "kannzennniixtuchi",
        "kanzennniixtsuti",
        "kannzennniixtsuti",
        "kanzennniixtsuchi",
        "kannzennniixtsuchi"
      ]
    },
    {
      "display": "ダンスダンスレボリューション",
      "yomi": "だんすだんすれぼりゅーしょん",
      "sentenceJp": "ダンスダンスレボリューション",
      "sentenceRm": [
        "dansudansureboryu-syonn",
        "dannsudansureboryu-syonn",
        "dansudannsureboryu-syonn",
        "dannsudannsureboryu-syonn",
        "dansudansureborixyu-syonn",
        "dannsudansureborixyu-syonn",
        "dansudannsureborixyu-syonn",
        "dannsudannsureborixyu-syonn",
        "dansudansureboryu-shonn",
        "dannsudansureboryu-shonn",
        "dansudannsureboryu-shonn",
        "dannsudannsureboryu-shonn",
        "dansudansureborixyu-shonn",
        "dannsudansureborixyu-shonn",
        "dansudannsureborixyu-shonn",
        "dannsudannsureborixyu-shonn",
        "dansudansureboryu-sixyonn",
        "dannsudansureboryu-sixyonn",
        "dansudannsureboryu-sixyonn",
        "dannsudannsureboryu-sixyonn",
        "dansudansureborixyu-sixyonn",
        "dannsudansureborixyu-sixyonn",
        "dansudannsureborixyu-sixyonn",
        "dannsudannsureborixyu-sixyonn",
        "dansudansureboryu-shixyonn",
        "dannsudansureboryu-shixyonn",
        "dansudannsureboryu-shixyonn",
        "dannsudannsureboryu-shixyonn",
        "dansudansureborixyu-shixyonn",
        "dannsudansureborixyu-shixyonn",
        "dansudannsureborixyu-shixyonn",
        "dannsudannsureborixyu-shixyonn"
      ]
    },
    {
      "display": "デバッグコンソール",
      "yomi": "でばっぐこんそーる",
      "sentenceJp": "デバッグコンソール",
      "sentenceRm": [
        "debaggukonso-ru",
        "debaxtugukonso-ru",
        "debaxtsugukonso-ru",
        "debaggukonnso-ru",
        "debaxtugukonnso-ru",
        "debaxtsugukonnso-ru"
      ]
    },
    {
      "display": "禁煙はじめました",
      "yomi": "きんえんはじめました",
      "sentenceJp": "禁煙はじめました",
      "sentenceRm": [
        "kinnenhazimemasita",
        "kinnennhazimemasita",
        "kinnenhajimemasita",
        "kinnennhajimemasita",
        "kinnenhazimemashita",
        "kinnennhazimemashita",
        "kinnenhajimemashita",
        "kinnennhajimemashita"
      ]
    },
    {
      "display": "熱中症対策",
      "yomi": "ねっちゅうしょうたいさく",
      "sentenceJp": "熱中症対策",
      "sentenceRm": [
        "nettyuusyoutaisaku",
        "necchuusyoutaisaku",
        "nettixyuusyoutaisaku",
        "necchixyuusyoutaisaku",
        "nextutyuusyoutaisaku",
        "nextuchuusyoutaisaku",
        "nextutixyuusyoutaisaku",
        "nextuchixyuusyoutaisaku",
        "nextsutyuusyoutaisaku",
        "nextsuchuusyoutaisaku",
        "nextsutixyuusyoutaisaku",
        "nextsuchixyuusyoutaisaku",
        "nettyuushoutaisaku",
        "necchuushoutaisaku",
        "nettixyuushoutaisaku",
        "necchixyuushoutaisaku",
        "nextutyuushoutaisaku",
        "nextuchuushoutaisaku",
        "nextutixyuushoutaisaku",
        "nextuchixyuushoutaisaku",
        "nextsutyuushoutaisaku",
        "nextsuchuushoutaisaku",
        "nextsutixyuushoutaisaku",
        "nextsuchixyuushoutaisaku",
        "nettyuusixyoutaisaku",
        "necchuusixyoutaisaku",
        "nettixyuusixyoutaisaku",
        "necchixyuusixyoutaisaku",
        "nextutyuusixyoutaisaku",
        "nextuchuusixyoutaisaku",
        "nextutixyuusixyoutaisaku",
        "nextuchixyuusixyoutaisaku",
        "nextsutyuusixyoutaisaku",
        "nextsuchuusixyoutaisaku",
        "nextsutixyuusixyoutaisaku",
        "nextsuchixyuusixyoutaisaku",
        "nettyuushixyoutaisaku",
        "necchuushixyoutaisaku",
        "nettixyuushixyoutaisaku",
        "necchixyuushixyoutaisaku",
        "nextutyuushixyoutaisaku",
        "nextuchuushixyoutaisaku",
        "nextutixyuushixyoutaisaku",
        "nextuchixyuushixyoutaisaku",
        "nextsutyuushixyoutaisaku",
        "nextsuchuushixyoutaisaku",
        "nextsutixyuushixyoutaisaku",
        "nextsuchixyuushixyoutaisaku"
      ]
    },
    {
      "display": "ツイッターで見た",
      "yomi": "ついったーでみた",
      "sentenceJp": "ツイッターで見た",
      "sentenceRm": [
        "tuitta-demita",
        "tsuitta-demita",
        "tuixtuta-demita",
        "tsuixtuta-demita",
        "tuixtsuta-demita",
        "tsuixtsuta-demita"
      ]
    }
  ]
}